CHANGELOG.rst
LICENSE
MANIFEST.in
README.rst
requirements.txt
setup.cfg
setup.py
django_grapesjs/__init__.py
django_grapesjs/settings.py
django_grapesjs.egg-info/PKG-INFO
django_grapesjs.egg-info/SOURCES.txt
django_grapesjs.egg-info/dependency_links.txt
django_grapesjs.egg-info/requires.txt
django_grapesjs.egg-info/top_level.txt
django_grapesjs/admin/__init__.py
django_grapesjs/admin/grepesjs_mixin.py
django_grapesjs/forms/__init__.py
django_grapesjs/forms/fields.py
django_grapesjs/forms/widgets.py
django_grapesjs/models/__init__.py
django_grapesjs/models/fields.py
django_grapesjs/static/css/django_grapesjs/grapes.min.css
django_grapesjs/static/css/django_grapesjs/grapesjs-plugin-filestack.css
django_grapesjs/static/css/django_grapesjs/grapesjs-preset-newsletter.css
django_grapesjs/static/css/django_grapesjs/grapesjs-preset-webpage.min.css
django_grapesjs/static/css/fonts/FontAwesome.otf
django_grapesjs/static/css/fonts/fontawesome-webfont.eot
django_grapesjs/static/css/fonts/fontawesome-webfont.svg
django_grapesjs/static/css/fonts/fontawesome-webfont.ttf
django_grapesjs/static/css/fonts/fontawesome-webfont.woff
django_grapesjs/static/css/fonts/fontawesome-webfont.woff2
django_grapesjs/static/css/fonts/main-fonts.eot
django_grapesjs/static/css/fonts/main-fonts.svg
django_grapesjs/static/css/fonts/main-fonts.ttf
django_grapesjs/static/css/fonts/main-fonts.woff
django_grapesjs/static/js/django_grapesjs/feather-aviary-editor.js
django_grapesjs/static/js/django_grapesjs/grapes.js
django_grapesjs/static/js/django_grapesjs/grapesjs-aviary.min.js
django_grapesjs/static/js/django_grapesjs/grapesjs-lory-slider.min.js
django_grapesjs/static/js/django_grapesjs/grapesjs-plugin-filestack.min.js
django_grapesjs/static/js/django_grapesjs/grapesjs-preset-newsletter.min.js
django_grapesjs/static/js/django_grapesjs/grapesjs-preset-webpage.min.js
django_grapesjs/static/js/django_grapesjs/grapesjs-tabs.min.js
django_grapesjs/template/__init__.py
django_grapesjs/templates/django_grapesjs/change_form.html
django_grapesjs/templates/django_grapesjs/default.html
django_grapesjs/templates/django_grapesjs/textarea.html
